{"data_mtime":1717396828,"dep_lines":[70,72,78,79,81,83,84,324,630,912,7,9,10,11,12,15,64,68,69,79,80,81,82,84,86,189,271,305,319,368,366,480,489,492,1,1,1,1,1,1,1,1,653,651,656],"dep_prios":[5,5,5,10,10,5,10,5,5,5,5,10,10,5,10,5,5,10,10,20,20,20,10,5,5,5,5,5,10,5,5,5,5,5,20,20,30,30,30,30,30,30,5,5,5],"dependencies":["urllib.parse","urllib.request","urllib.error","http.client","xmlrpc.client","html.parser","html.entities","collections.abc","importlib.util","logging.config","__future__","os","re","shutil","sys","ssl","io","builtins","configparser","http","urllib","xmlrpc","queue","html","itertools","types","zipfile","platform","sysconfig","codecs","tokenize","cgi","collections","reprlib","pyexpat.model","pyexpat.errors","_collections_abc","_typeshed","abc","enum","importlib","typing"],"hash":"527fae201bf2d36c3e0f6ebb386e15121b9d76a5a02a3f67364c5596d01bef9c","id":"pip._vendor.distlib.compat","ignore_all":true,"interface_hash":"0c89841a3bac1968a3e735418ed47092777cf8e5ce2e34f8bf5a5cc87a19380f","mtime":1706953690,"options":{"allow_redefinition":false,"allow_untyped_globals":false,"always_false":[],"always_true":[],"bazel":false,"check_untyped_defs":false,"disable_bytearray_promotion":false,"disable_error_code":[],"disable_memoryview_promotion":false,"disabled_error_codes":[],"disallow_any_decorated":false,"disallow_any_explicit":false,"disallow_any_expr":false,"disallow_any_generics":false,"disallow_any_unimported":false,"disallow_incomplete_defs":false,"disallow_subclassing_any":false,"disallow_untyped_calls":false,"disallow_untyped_decorators":false,"disallow_untyped_defs":false,"enable_error_code":[],"enabled_error_codes":[],"extra_checks":false,"follow_imports":"normal","follow_imports_for_stubs":false,"ignore_errors":false,"ignore_missing_imports":false,"implicit_optional":false,"implicit_reexport":true,"local_partial_types":false,"mypyc":false,"old_type_inference":false,"platform":"linux","plugins":[],"strict_concatenate":false,"strict_equality":false,"strict_optional":true,"warn_no_return":true,"warn_return_any":false,"warn_unreachable":false,"warn_unused_ignores":false},"path":"/home/hampuz/anaconda3/lib/python3.11/site-packages/pip/_vendor/distlib/compat.py","plugin_data":null,"size":41487,"suppressed":["dummy_thread","thread","_abcoll"],"version_id":"1.10.0"}