{"data_mtime":1717396829,"dep_lines":[71,53,79,80,53,78,79,78,52,48,52,63,64,73,74,75,76,1,1,1,1,1,1,1,1,1,1,1,50,51,50],"dep_prios":[5,10,10,5,20,10,20,20,5,5,20,5,5,10,10,10,10,5,20,20,30,30,30,30,30,30,30,30,10,10,20],"dependencies":["pip._vendor.urllib3.packages.backports.makefile","cryptography.hazmat.backends.openssl.backend","pip._vendor.urllib3.packages.six","pip._vendor.urllib3.util.ssl_","cryptography.hazmat.backends.openssl","pip._vendor.urllib3.util","pip._vendor.urllib3.packages","pip._vendor.urllib3","cryptography.x509","__future__","cryptography","io","socket","logging","ssl","sys","warnings","builtins","pyexpat.model","pyexpat.errors","_collections_abc","_typeshed","_warnings","abc","enum","pip._vendor.urllib3.packages.backports","types","typing"],"hash":"843261e0c87263fa7ea0a9457187106954110efe86326046b96f728f1c9e7a33","id":"pip._vendor.urllib3.contrib.pyopenssl","ignore_all":true,"interface_hash":"627ecd7401076f2a80c03385c6fc6bb50ab2098aa7c4e5044fb27a436fe572a2","mtime":1706953690,"options":{"allow_redefinition":false,"allow_untyped_globals":false,"always_false":[],"always_true":[],"bazel":false,"check_untyped_defs":false,"disable_bytearray_promotion":false,"disable_error_code":[],"disable_memoryview_promotion":false,"disabled_error_codes":[],"disallow_any_decorated":false,"disallow_any_explicit":false,"disallow_any_expr":false,"disallow_any_generics":false,"disallow_any_unimported":false,"disallow_incomplete_defs":false,"disallow_subclassing_any":false,"disallow_untyped_calls":false,"disallow_untyped_decorators":false,"disallow_untyped_defs":false,"enable_error_code":[],"enabled_error_codes":[],"extra_checks":false,"follow_imports":"normal","follow_imports_for_stubs":false,"ignore_errors":false,"ignore_missing_imports":false,"implicit_optional":false,"implicit_reexport":true,"local_partial_types":false,"mypyc":false,"old_type_inference":false,"platform":"linux","plugins":[],"strict_concatenate":false,"strict_equality":false,"strict_optional":true,"warn_no_return":true,"warn_return_any":false,"warn_unreachable":false,"warn_unused_ignores":false},"path":"/home/hampuz/anaconda3/lib/python3.11/site-packages/pip/_vendor/urllib3/contrib/pyopenssl.py","plugin_data":null,"size":17081,"suppressed":["OpenSSL.crypto","OpenSSL.SSL","OpenSSL"],"version_id":"1.10.0"}